tstl/__init__.py
tstl/analyzeprovenance.py
tstl/analyzeswarm.py
tstl/calibrate.py
tstl/directedswarm.py
tstl/exhaust.py
tstl/fpf.py
tstl/fromafl.py
tstl/generalize.py
tstl/graph.py
tstl/harnessmaker.py
tstl/makecorpus.py
tstl/markov.py
tstl/provenance.py
tstl/randomtester.py
tstl/reduce.py
tstl/replay.py
tstl/runregressions.py
tstl/smallcheck.py
tstl/standalone.py
tstl/tocorpus.py
tstl/triage.py
tstl/tstl_afl.py
tstl/tstl_afl_fuzz.py
tstl/static/boilerplate
tstl/static/boilerplate_cov
tstl-1.2.39.dist-info/LICENSE
tstl-1.2.39.dist-info/METADATA
tstl-1.2.39.dist-info/WHEEL
tstl-1.2.39.dist-info/entry_points.txt
tstl-1.2.39.dist-info/top_level.txt
tstl-1.2.39.dist-info/RECORD
