Metadata-Version: 2.1
Name: tstl
Version: 1.2.39
Summary: Template scripting testing language (TSTL)
Home-page: https://github.com/agroce/tstl
License: MIT
Keywords: testing tstl
Platform: UNKNOWN
Classifier: Intended Audience :: Developers
Classifier: Development Status :: 4 - Beta
Classifier: Programming Language :: Python :: 2
Classifier: Programming Language :: Python :: 3
Requires-Dist: coverage (==4.5.2)
